README.txt
setup.cfg
setup.py
docs/HISTORY.txt
raptus/__init__.py
raptus.browsermessage.egg-info/PKG-INFO
raptus.browsermessage.egg-info/SOURCES.txt
raptus.browsermessage.egg-info/dependency_links.txt
raptus.browsermessage.egg-info/entry_points.txt
raptus.browsermessage.egg-info/namespace_packages.txt
raptus.browsermessage.egg-info/not-zip-safe
raptus.browsermessage.egg-info/requires.txt
raptus.browsermessage.egg-info/top_level.txt
raptus/browsermessage/__init__.py
raptus/browsermessage/config.py
raptus/browsermessage/configure.zcml
raptus/browsermessage/Extensions/Install.py
raptus/browsermessage/Extensions/__init__.py
raptus/browsermessage/browser/__init__.py
raptus/browsermessage/browser/configlet.pt
raptus/browsermessage/browser/configlet.py
raptus/browsermessage/browser/configure.zcml
raptus/browsermessage/browser/icon.gif
raptus/browsermessage/browser/icons.psd
raptus/browsermessage/browser/viewlet.pt
raptus/browsermessage/browser/viewlet.py
raptus/browsermessage/i18n/plone-raptus.browsermessage-de.po
raptus/browsermessage/i18n/plone-raptus.browsermessage.pot
raptus/browsermessage/i18n/raptus.browsermessage-de.po
raptus/browsermessage/i18n/raptus.browsermessage.pot
raptus/browsermessage/profiles/default/actionicons.xml
raptus/browsermessage/profiles/default/actions.xml
raptus/browsermessage/profiles/default/controlpanel.xml
raptus/browsermessage/profiles/default/cssregistry.xml
raptus/browsermessage/profiles/default/metadata.xml
raptus/browsermessage/profiles/default/propertiestool.xml
raptus/browsermessage/profiles/default/skins.xml
raptus/browsermessage/profiles/default/viewlets.xml
raptus/browsermessage/profiles/uninstall/controlpanel.xml
raptus/browsermessage/profiles/uninstall/cssregistry.xml
raptus/browsermessage/profiles/uninstall/viewlets.xml
raptus/browsermessage/skins/browsermessage/browsermessage.css.dtml
raptus/browsermessage/skins/browsermessage/browsermessage.js
raptus/browsermessage/skins/browsermessage/browsermessage_ignore.py
raptus/browsermessage/skins/browsermessage/chrome.png
raptus/browsermessage/skins/browsermessage/firefox.png
raptus/browsermessage/skins/browsermessage/opera.png
raptus/browsermessage/skins/browsermessage/safari.png