Metadata-Version: 1.0
Name: raptus.browsermessage
Version: 0.1
Summary: Configurable upgrade message for visitors using a outdated browser
Home-page: http://raptus.com
Author: Raptus AG
Author-email: skaeser@raptus.com
License: GPL
Platform: UNKNOWN
Classifier: Programming Language :: Python
Classifier: Topic :: Software Development :: Libraries :: Python Modules
